adestis_netbox_applications/__init__.py
adestis_netbox_applications/navigation.py
adestis_netbox_applications/urls.py
adestis_netbox_applications/api/__init__.py
adestis_netbox_applications/api/urls.py
adestis_netbox_applications/api/views.py
adestis_netbox_applications/api/serializers/__init__.py
adestis_netbox_applications/api/serializers/application_serializer.py
adestis_netbox_applications/api/serializers/application_types_serializer.py
adestis_netbox_applications/api/serializers/software_serializer.py
adestis_netbox_applications/filtersets/__init__.py
adestis_netbox_applications/filtersets/application.py
adestis_netbox_applications/filtersets/application_types.py
adestis_netbox_applications/filtersets/software.py
adestis_netbox_applications/forms/__init__.py
adestis_netbox_applications/forms/application.py
adestis_netbox_applications/forms/application_types.py
adestis_netbox_applications/forms/software.py
adestis_netbox_applications/migrations/0001_initial.py
adestis_netbox_applications/migrations/0002_rename_application_installedapplication.py
adestis_netbox_applications/migrations/0003_rename_installedapplication_application.py
adestis_netbox_applications/migrations/0004_rename_application_installedapplication.py
adestis_netbox_applications/migrations/0005_rename_tenant_groups_installedapplication_tenant_group_and_more.py
adestis_netbox_applications/migrations/0006_alter_installedapplication_options_and_more.py
adestis_netbox_applications/migrations/0007_installedapplicationtypes.py
adestis_netbox_applications/migrations/0008_installedapplication_application_types.py
adestis_netbox_applications/migrations/0009_installedapplicationtypes_installedapplication.py
adestis_netbox_applications/migrations/0010_installedapplicationtypes_description_and_more.py
adestis_netbox_applications/migrations/0011_alter_installedapplication_application_types.py
adestis_netbox_applications/migrations/0012_alter_installedapplicationtypes_slug.py
adestis_netbox_applications-1.0.23.dist-info/LICENSE
adestis_netbox_applications-1.0.23.dist-info/METADATA
adestis_netbox_applications-1.0.23.dist-info/WHEEL
adestis_netbox_applications-1.0.23.dist-info/top_level.txt
adestis_netbox_applications-1.0.23.dist-info/RECORD
