Metadata-Version: 2.1
Name: adestis-netbox-applications
Version: 1.0.23
Summary: ADESTIS Application Management
Home-page: https://github.com/an-adestis/netbox_applications
Author: ADESTIS GmbH
Author-email: pypi@adestis.de
License: GPL-3.0-only
Keywords: netbox,netbox-plugin,plugin
License-File: LICENSE
Requires-Dist: adestis-netbox-certificate-management
